{
    "duration_construct_s": 181.985886,
    "duration_prune_s": 0.0,
    "hyperparams": {
        "adjust_C_p": true,
        "btm": false,
        "expansion_budget_modifier": 50,
        "exploration_c": 0.1,
        "max_indegree": 3,
        "rollout_depth": 2,
        "rollout_policy": "random",
        "time_budget_s": -1
    },
    "hyperparams_id": 1,
    "instance_metadata": {
        "name": "sachs",
        "reg_type": "GPR",
        "rlbic_num_edges": 49,
        "root_path": "/experiment_data/datasets/sachs",
        "rvar_type": "continuous",
        "transpose": false
    },
    "results": {
        "construct": {
            "edges": [
                [
                    1,
                    0
                ],
                [
                    1,
                    2
                ],
                [
                    1,
                    3
                ],
                [
                    1,
                    4
                ],
                [
                    1,
                    5
                ],
                [
                    1,
                    6
                ],
                [
                    1,
                    7
                ],
                [
                    1,
                    8
                ],
                [
                    1,
                    9
                ],
                [
                    2,
                    0
                ],
                [
                    2,
                    3
                ],
                [
                    2,
                    4
                ],
                [
                    3,
                    0
                ],
                [
                    4,
                    3
                ],
                [
                    4,
                    10
                ],
                [
                    5,
                    6
                ],
                [
                    7,
                    5
                ],
                [
                    7,
                    6
                ],
                [
                    7,
                    9
                ],
                [
                    8,
                    2
                ],
                [
                    8,
                    5
                ],
                [
                    8,
                    7
                ],
                [
                    8,
                    9
                ],
                [
                    8,
                    10
                ],
                [
                    9,
                    2
                ],
                [
                    9,
                    4
                ],
                [
                    9,
                    10
                ]
            ],
            "fdr": 0.5925925925925926,
            "fpr": 0.42105263157894735,
            "pred_size": 27,
            "reward": 17.841352140562623,
            "shd": 19,
            "tpr": 0.6470588235294118
        },
        "ground_truth": {
            "edges": [
                [
                    0,
                    1
                ],
                [
                    1,
                    5
                ],
                [
                    2,
                    3
                ],
                [
                    2,
                    4
                ],
                [
                    4,
                    3
                ],
                [
                    5,
                    6
                ],
                [
                    7,
                    0
                ],
                [
                    7,
                    1
                ],
                [
                    7,
                    5
                ],
                [
                    7,
                    6
                ],
                [
                    7,
                    9
                ],
                [
                    7,
                    10
                ],
                [
                    8,
                    0
                ],
                [
                    8,
                    1
                ],
                [
                    8,
                    7
                ],
                [
                    8,
                    9
                ],
                [
                    8,
                    10
                ]
            ],
            "fdr": 0.0,
            "fpr": 0.0,
            "pred_size": 17,
            "reward": 13.2638284460602,
            "shd": 0,
            "tpr": 1.0
        },
        "prune_cam": {
            "edges": [
                [
                    1,
                    0
                ],
                [
                    2,
                    3
                ],
                [
                    2,
                    4
                ],
                [
                    4,
                    3
                ],
                [
                    5,
                    6
                ],
                [
                    7,
                    5
                ],
                [
                    7,
                    6
                ],
                [
                    8,
                    9
                ],
                [
                    8,
                    10
                ],
                [
                    9,
                    10
                ]
            ],
            "fdr": 0.2,
            "fpr": 0.05263157894736842,
            "pred_size": 10,
            "reward": 11.863084782520849,
            "shd": 10,
            "tpr": 0.47058823529411764
        }
    }
}